t3/__init__.py
t3/__main__.py
t3/arguments.py
t3/entrypoint.py
t3/assets/__init__.py
t3/assets/path.py
t3/assets/COLORALPHA/MI_SFX 42.s16.wav
t3/assets/COLORALPHA/MI_SFX 42.wav
t3/assets/GowunDodum/GowunDodum-Regular.ttf
t3/assets/GowunDodum/OFL.txt
t3/assets/MDI/LICENSE
t3/assets/MDI/arrow-left-bold-hovered.png
t3/assets/MDI/arrow-left-bold-normal.png
t3/assets/MDI/arrow-left-bold-pressed.png
t3/assets/MDI/arrow-right-bold-hovered.png
t3/assets/MDI/arrow-right-bold-normal.png
t3/assets/MDI/arrow-right-bold-pressed.png
t3/assets/MDI/exit-run-hovered.png
t3/assets/MDI/exit-run-normal.png
t3/assets/MDI/exit-run-pressed.png
t3/assets/MDI/refresh-hovered.png
t3/assets/MDI/refresh-normal.png
t3/assets/MDI/refresh-pressed.png
t3/assets/Shapeforms/BUTTON_05.s16.wav
t3/assets/Shapeforms/BUTTON_05.wav
t3/assets/Shapeforms/FUI Ping Triplet Echo.wav
t3/assets/Shapeforms/Shapeforms License Agreement.pdf
t3/assets/Shapeforms/Wallet Close.wav
t3/assets/__pycache__/__init__.cpython-39.pyc
t3/assets/__pycache__/path.cpython-39.pyc
t3/color/__init__.py
t3/color/color_tuple.py
t3/color/palette/__init__.py
t3/color/palette/flat_ui.py
t3/color/palette/paper_pixels.py
t3/context/__init__.py
t3/context/context.py
t3/logging/__init__.py
t3/logging/colored_formatter.py
t3/logging/logging.py
t3/module/__init__.py
t3/module/path.py
t3/objects/__init__.py
t3/objects/block.py
t3/objects/board.py
t3/objects/game.py
t3/objects/history.py
t3/objects/matrix.py
t3/stages/__init__.py
t3/stages/stage.py
t3/stages/stage00.py
t3/stages/stage01.py
t3/stages/stage02.py
t3/stages/stage03.py
t3/stages/stage04.py
t3/stages/stage05.py
t3/stages/stage06.py
t3/stages/stage07.py
t3/stages/stage08.py
t3/stages/stage09.py
t3/stages/stage10.py
t3/stages/stages.py
t3/theme/__init__.py
t3/theme/flat.py
t3/theme/theme.py
t3/variables/__init__.py
t3/variables/block.py
t3/variables/board.py
t3/variables/fonts.py
t3/www/__init__.py
turn_the_tricks-0.0.1.dist-info/LICENSE
turn_the_tricks-0.0.1.dist-info/METADATA
turn_the_tricks-0.0.1.dist-info/WHEEL
turn_the_tricks-0.0.1.dist-info/entry_points.txt
turn_the_tricks-0.0.1.dist-info/top_level.txt
turn_the_tricks-0.0.1.dist-info/RECORD
